{"key": "HomeNew", "image": "", "elements": [{"label": "Welcome Back", "type": "label", "key": "WelcomeBack"}, {"label": "Hi!", "type": "label", "key": "homeWelcome"}, {"label": "Prayer Time", "type": "label", "key": "PrayerTime"}, {"label": "Keep track of prayer times and never miss out on a prayer again.", "type": "label", "key": "InsanCardprompt"}, {"label": "You’re about to remove the Prayer function. You can turn it back on in the “Customize” menu in your account settings", "type": "label", "key": "closePrayerCard"}, {"label": "Alert", "type": "label", "key": "prayerAlert"}, {"label": "YES", "type": "label", "key": "prayerAlertYes"}, {"label": "NO", "type": "label", "key": "prayerAlertNo"}, {"label": "Get Started", "type": "label", "key": "GetStarted"}, {"label": "Challenge Yourself", "type": "label", "key": "ChallengeYourself"}, {"label": "Join this timed challenge for a chance to win an iPhone X!", "type": "label", "key": "Challengeprompt"}, {"label": "News & Update", "type": "label", "key": "NewsUpdate"}]}