{
	"key": "CreatePost",
	"image": "",
	"elements": [{
		"label": "Create post",
		"type": "label",
		"key": "createPost"
	}, {
		"label": "Choose Classification",
		"type": "label",
		"key": "chooseClassification"
	}, {
		"label": "Create a Community",
		"type": "label",
		"key": "createCommunity"
	}, {
		"label": "Choose Channel",
		"type": "label",
		"key": "chooseChannel"
	}, {
		"label": "Enter Post Title",
		"type": "label",
		"key": "postTitle"
	}, {
		"label": "Upload Image",
		"type": "label",
		"key": "uploadImage"
	}, {
		"label": "Enter Post Description",
		"type": "label",
		"key": "enterPostDescription"
	}, {
		"label": "Health Channels",
		"type": "label",
		"key": "healthChannels"
	}, {
		"label": "Wealth Channels",
		"type": "label",
		"key": "wealthChannels"
	}, {
		"label": "Error No Channels Available in this classification",
		"type": "error",
		"key": "noChannelAvailable"
	}, {
		"label": "Size Limit Exceeded",
		"type": "error",
		"key": "sizeLimit"
	}, {
		"label": "Please select image less than 250KB in size!",
		"type": "error",
		"key": "sizeLimit250KB"
	}, {
		"label": "Please select file less than 500KB in size!",
		"type": "error",
		"key": "sizeLimit500KB"
	}, {
		"label": "Please select file less than 1MB in size!",
		"type": "error",
		"key": "sizeLimit1MB"
	}, {
		"label": "Please select file less than 5MB in size!",
		"type": "error",
		"key": "sizeLimit5MB"
	}, {
		"label": "Please select only html file",
		"type": "error",
		"key": "htmlOnly"
	}, {
		"label": "Upload Image doc id is empty",
		"type": "error",
		"key": "uploadImageEmpty"
	}, {
		"label": "Upload content doc id is empty",
		"type": "error",
		"key": "uploadContentEmpty"
	}, {
		"label": "Please select image of dimension",
		"type": "label",
		"key": "imageDimension1"
	}, {
		"label": "and size less than",
		"type": "label",
		"key": "imageDimension2"
	}, {
		"label": "KB",
		"type": "label",
		"key": "imageDimension3"
	}, {
		"label": "Error",
		"type": "label",
		"key": "error"
	}, {
		"label": "Image Upload Failed",
		"type": "label",
		"key": "imageUploadFailed"
	}, {
		"label": "Sequence Range From 0-10k.",
		"type": "label",
		"key": "sequenceRange"
	}, {
		"label": "Enter Sequence number",
		"type": "label",
		"key": "sequenceNumber"
	}]
}