{
  "label": "LA Product Names",
  "image": "",
  "key": "laProductNames",
  "elements": [
    {
      "key": "CC1",
      "label": "Crisis Cover - CC1",
      "type": "label"
    },
    {
      "key": "CM1",
      "label": "Pru VN - CIE",
      "type": "label"
    },
    {
      "key": "CM2",
      "label": "Pru VN Enhanced CIE",
      "type": "label"
    },
    {
      "key": "CY1",
      "label": "Cancer (Online)",
      "type": "label"
    },
    {
      "key": "CYR",
      "label": "Cancer (Telco)",
      "type": "label"
    },
    {
      "key": "EA1",
      "label": " Pru VN - Anticipated Endowment",
      "type": "label"
    },
    {
      "key": "EA2",
      "label": "Pru VN - Increasing PruCash",
      "type": "label"
    },
    {
      "key": "EA3",
      "label": "Pru VN - Wedding",
      "type": "label"
    },
    {
      "key": "EA4",
      "label": "Pru VN - PCD",
      "type": "label"
    },
    {
      "key": "EA5",
      "label": "Pru VN - PCB",
      "type": "label"
    },
    {
      "key": "EA6",
      "label": "Pru VN - FLEXICASH",
      "type": "label"
    },
    {
      "key": "EE1",
      "label": " Pru VN - Juvenile Endowment",
      "type": "label"
    },
    {
      "key": "EM1",
      "label": "Pru VN - Master",
      "type": "label"
    },
    {
      "key": "EN1",
      "label": "Pru VN - Endowment",
      "type": "label"
    },
    {
      "key": "EN2",
      "label": "Pru VN - Enhanced Endowment",
      "type": "label"
    },
    {
      "key": "EN3",
      "label": "Pru VN - Property",
      "type": "label"
    },
    {
      "key": "EN4",
      "label": "Pru VN - Limited pay Endowment",
      "type": "label"
    },
    {
      "key": "EN5",
      "label": "Pru VN - Lifetime Endowment",
      "type": "label"
    },
    {
      "key": "EN6",
      "label": "Pvn Property Simple Package",
      "type": "label"
    },
    {
      "key": "EN7",
      "label": "PVN Pru Property for TM/DM",
      "type": "label"
    },
    {
      "key": "EU1",
      "label": "Pru VN - PruScholar University",
      "type": "label"
    },
    {
      "key": "EU2",
      "label": "Pru VN - Scholar Single Prem",
      "type": "label"
    },
    {
      "key": "EU3",
      "label": "Pru VN - PTE",
      "type": "label"
    },
    {
      "key": "EU4",
      "label": "Pru VN - PTE Revamp",
      "type": "label"
    },
    {
      "key": "EU5",
      "label": "PRU-EDUSAVER",
      "type": "label"
    },
    {
      "key": "IP1",
      "label": "IP-Individual pension",
      "type": "label"
    },
    {
      "key": "MI1",
      "label": "PRU VN Micro Insurance",
      "type": "label"
    },
    {
      "key": "PA1",
      "label": "Pru VN - Success",
      "type": "label"
    },
    {
      "key": "PE1",
      "label": "Pru VN - Family",
      "type": "label"
    },
    {
      "key": "PE2",
      "label": "Pru VN - Truong Khang",
      "type": "label"
    },
    {
      "key": "PE3",
      "label": "Pru VN - Lady",
      "type": "label"
    },
    {
      "key": "PE4",
      "label": "Pru VN - EPS Package",
      "type": "label"
    },
    {
      "key": "PJ1",
      "label": "Pru VN - Future",
      "type": "label"
    },
    {
      "key": "PR1",
      "label": "Pru VN - Retire Easy Reg",
      "type": "label"
    },
    {
      "key": "PR2",
      "label": "Pru VN - Retire Easy Ltd",
      "type": "label"
    },
    {
      "key": "PS1",
      "label": "Pru VN-Pru SmartSave(Limited)",
      "type": "label"
    },
    {
      "key": "PS2",
      "label": "Pru VN-Pru SmartSave(Single)",
      "type": "label"
    },
    {
      "key": "PT2",
      "label": "Pru VN - An Nghiep 2",
      "type": "label"
    },
    {
      "key": "RO1",
      "label": "Standalone Personal Accident",
      "type": "label"
    },
    {
      "key": "TA2",
      "label": "Pru VN - Binh An",
      "type": "label"
    },
    {
      "key": "TA3",
      "label": "Pru VN Level Term Stand alone",
      "type": "label"
    },
    {
      "key": "TA9",
      "label": "Personal Accident Standalone",
      "type": "label"
    },
    {
      "key": "TH1",
      "label": "Level Term Stand Alone",
      "type": "label"
    },
    {
      "key": "TL1",
      "label": "Pru VN - Return of Premium",
      "type": "label"
    },
    {
      "key": "TL2",
      "label": " Pru VN - An Nghiep",
      "type": "label"
    },
    {
      "key": "TL3",
      "label": "Pru VN - Hung Nghiep",
      "type": "label"
    },
    {
      "key": "TL4",
      "label": "Pru VN - Limited pay MRTA",
      "type": "label"
    },
    {
      "key": "TL5",
      "label": "Pru VN - MRTA Single Prem",
      "type": "label"
    },
    {
      "key": "TL8",
      "label": "Pru VN - Return of Premium ",
      "type": "label"
    },
    {
      "key": "TM1",
      "label": "Pru VN - An Thinh",
      "type": "label"
    },
    {
      "key": "UR2",
      "label": "Regular Unit-linked",
      "type": "label"
    },
    {
      "key": "UR4",
      "label": "ILP 2015 - Prulink",
      "type": "label"
    },
    {
      "key": "UR5",
      "label": "ILP 2016 - Prulink",
      "type": "label"
    },
    {
      "key": "UR6",
      "label": "ILP 2017 - Prulink",
      "type": "label"
    },
    {
      "key": "VL2",
      "label": "UL-Target premium concept",
      "type": "label"
    },
    {
      "key": "VL3",
      "label": "UL-RegularPremium Revamp",
      "type": "label"
    },
    {
      "key": "VL4",
      "label": "UL-SinglePremium Revamp",
      "type": "label"
    },
    {
      "key": "VL5",
      "label": "New ULP Regular Premium 2016",
      "type": "label"
    },
    {
      "key": "VL6",
      "label": "New ULP with UDR ",
      "type": "label"
    },
    {
      "key": "VL7",
      "label": "ULCI 2019 ",
      "type": "label"
    },
    {
      "key": "VR1",
      "label": "VL Reg - VR1",
      "type": "label"
    },
    {
      "key": "VS1",
      "label": "VL Sin - VS1",
      "type": "label"
    },
    {
      "key": "WL1",
      "label": "Pru VN - Whole Life",
      "type": "label"
    }
  ]
}